lambda-logger/__init__.py
lambda-logger/_nbdev.py
lambda-logger/core.py
lambda_log_service/__init__.py
lambda_log_service/_nbdev.py
lambda_log_service/core.py
lambda_logger/__init__.py
lambda_logger/_nbdev.py
lambda_logger/core.py
lambda_logger-0.0.12.dist-info/LICENSE
lambda_logger-0.0.12.dist-info/METADATA
lambda_logger-0.0.12.dist-info/WHEEL
lambda_logger-0.0.12.dist-info/entry_points.txt
lambda_logger-0.0.12.dist-info/top_level.txt
lambda_logger-0.0.12.dist-info/RECORD
