Metadata-Version: 2.1
Name: lambda-logger
Version: 0.0.12
Summary: A project that integrates both sentry and aws-lambda-power
Home-page: https://github.com/jeremytee97/lambda_logger/tree/master/
Author: Jeremy
Author-email: jeremytee97@gmail.com
License: Apache Software License 2.0
Keywords: sentry aws-lambda-powertools
Platform: UNKNOWN
Classifier: Development Status :: 3 - Alpha
Classifier: Intended Audience :: Developers
Classifier: License :: OSI Approved :: Apache Software License
Classifier: Natural Language :: English
Classifier: Programming Language :: Python :: 3.6
Classifier: Programming Language :: Python :: 3.7
Classifier: Programming Language :: Python :: 3.8
Requires-Python: >=3.6
Requires-Dist: aws-lambda-powertools (>=1.10.1)
Requires-Dist: sentry-sdk (>=0.19.5)
